mcpadapt/__init__.py
mcpadapt/core.py
mcpadapt/crewai_adapter.py
mcpadapt/google_genai_adapter.py
mcpadapt/langchain_adapter.py
mcpadapt/py.typed
mcpadapt/smolagents_adapter.py
mcpadapt/utils/__init__.py
mcpadapt/utils/modeling.py
mcpadapt-0.1.17.dist-info/METADATA
mcpadapt-0.1.17.dist-info/WHEEL
mcpadapt-0.1.17.dist-info/licenses/LICENSE
mcpadapt-0.1.17.dist-info/RECORD
